{
    "wallpaper": "/home/neo/Wallpaper/wall20.png",
    "alpha": "100",
    "special": {
        "background": "#0A0915",
        "foreground": "#a4cbec",
        "cursor": "#a4cbec"
    },
    "colors": {
        "color0": "#0A0915",
        "color1": "#074F8F",
        "color2": "#1261A9",
        "color3": "#554BB7",
        "color4": "#1A71D0",
        "color5": "#A466DF",
        "color6": "#1498ED",
        "color7": "#a4cbec",
        "color8": "#728ea5",
        "color9": "#074F8F",
        "color10": "#1261A9",
        "color11": "#554BB7",
        "color12": "#1A71D0",
        "color13": "#A466DF",
        "color14": "#1498ED",
        "color15": "#a4cbec"
    }
}